{
  "entities": [
    {
      "behaviors": [
        {
          "isNative": true,
          "name": "Transform",
          "properties": {
            "angle": 0.0,
            "sx": 1.0,
            "sy": 1.0,
            "vx": 0.0,
            "vy": 0.0,
            "x": 0.0,
            "y": 0.0
          }
        },
        {
          "name": "GameDirector"
        }
      ],
      "drawOrder": -1000,
      "id": 1,
      "name": "GameDirector",
      "scripts": [
        "GameDirector"
      ],
      "transform": {
        "angle": 0.0,
        "sx": 1.0,
        "sy": 1.0,
        "vx": 0.0,
        "vy": 0.0,
        "x": 0.0,
        "y": 0.0
      },
      "updateOrder": 100
    },
    {
      "behaviors": [
        {
          "isNative": true,
          "name": "Transform",
          "properties": {
            "angle": 270.0,
            "sx": 1.0,
            "sy": 1.0,
            "vx": 0.0,
            "vy": 0.0,
            "x": 343.5,
            "y": 245.5
          }
        },
        {
          "name": "Ship"
        },
        {
          "name": "Sprite",
          "properties": {
            "image": "assets/ships_human.png"
          }
        }
      ],
      "drawOrder": 2,
      "id": 2,
      "name": "Player",
      "scripts": [
        "Ship",
        {
          "behavior": "Sprite",
          "properties": {
            "image": "assets/ships_human.png"
          }
        }
      ],
      "transform": {
        "angle": 270.0,
        "sx": 1.0,
        "sy": 1.0,
        "vx": 0.0,
        "vy": 0.0,
        "x": 343.5,
        "y": 245.5
      },
      "updateOrder": 0
    },
    {
      "behaviors": [
        {
          "isNative": true,
          "name": "Transform",
          "properties": {
            "angle": 0.0,
            "sx": 1.0,
            "sy": 1.0,
            "vx": 0.0,
            "vy": 0.0,
            "x": 0.0,
            "y": 0.0
          }
        },
        {
          "name": "VFX"
        }
      ],
      "drawOrder": 500,
      "id": 3,
      "name": "VFX",
      "scripts": [
        "VFX"
      ],
      "transform": {
        "angle": 0.0,
        "sx": 1.0,
        "sy": 1.0,
        "vx": 0.0,
        "vy": 0.0,
        "x": 0.0,
        "y": 0.0
      },
      "updateOrder": 50
    },
    {
      "behaviors": [
        {
          "isNative": true,
          "name": "Transform",
          "properties": {
            "angle": 0.0,
            "sx": 1.0,
            "sy": 1.0,
            "vx": 0.0,
            "vy": 0.0,
            "x": 0.0,
            "y": 0.0
          }
        },
        {
          "name": "HUD"
        }
      ],
      "drawOrder": 999,
      "id": 4,
      "name": "HUD",
      "scripts": [
        "HUD"
      ],
      "transform": {
        "angle": 0.0,
        "sx": 1.0,
        "sy": 1.0,
        "vx": 0.0,
        "vy": 0.0,
        "x": 0.0,
        "y": 0.0
      },
      "updateOrder": 999
    },
    {
      "behaviors": [
        {
          "isNative": true,
          "name": "Transform",
          "properties": {
            "angle": 0.0,
            "sx": 1.0,
            "sy": 1.0,
            "vx": 0.0,
            "vy": 0.0,
            "x": 30.0,
            "y": 0.0
          }
        },
        {
          "name": "NewBehavior"
        }
      ],
      "drawOrder": 0,
      "id": 5,
      "name": "Entity",
      "parentId": 2,
      "scripts": [
        "NewBehavior"
      ],
      "transform": {
        "angle": 0.0,
        "sx": 1.0,
        "sy": 1.0,
        "vx": 0.0,
        "vy": 0.0,
        "x": 30.0,
        "y": 0.0
      },
      "updateOrder": 0
    }
  ]
}
